{"categories":{},"sliders":{"-Oh3TziDSbfixinh2z2K":{"img":"https://i.ibb.co/7JQGF2Vh/student-wearing-headphones-holding-notebook-practicing-before-exam.jpg","type":"link","value":""}},"home_buttons":{},"notifications":{"-OiYz3c6as26kA5LqqKE":{"desc":"Subi dost teligram join krlo","img":"https://i.ibb.co/dwHtM9bz/Telegram-logo-svg.png","timestamp":1770409675847,"title":"Join teligram ","type":"link","value":"https://t.me/Testgurutg"}},"popup_notification":{},"admin_settings":{"ad_smart_link":"https://omg10.com/4/10022830","ad_smart_link_on":false,"ad_unlock_duration_mins":1,"discount_percent":51,"free_days":1,"img_size_opt":"100px","img_size_q":"100px","login_enabled":false,"monetag_new_func":"show_10055173","monetag_new_script":"<script src='//libtl.com/sdk.js' data-zone='10055173' data-sdk='show_10055173'></script>","revenue_offset":7,"rzp_key":"rzp_live_Rm30E7uT81eawu","rzp_key_new":"","rzp_secret":"","vip_days":365,"vip_price":49}}